py4design/__init__.py
py4design/analysisrulepalette.py
py4design/buildingformeval.py
py4design/citygml2eval.py
py4design/gml3dmodel.py
py4design/gmlparameterise.py
py4design/gmlparmpalette.py
py4design/massing2citygml.py
py4design/shapeattributes.py
py4design/shp2citygml.py
py4design/skyviewfactor.py
py4design/templaterulepalette.py
py4design/urbanformeval.py
py4design/urbangeom.py
py4design/utility.py
py4design/py2energyplus/__init__.py
py4design/py2energyplus/idf_writer.py
py4design/py2radiance/__init__.py
py4design/py2radiance/base.rad
py4design/py2radiance/write_rad.py
py4design/py3dmodel/__init__.py
py4design/py3dmodel/calculate.py
py4design/py3dmodel/construct.py
py4design/py3dmodel/export_collada.py
py4design/py3dmodel/fetch.py
py4design/py3dmodel/modify.py
py4design/py3dmodel/utility.py
py4design/py3dmodel/OCCUtils/Common.py
py4design/py3dmodel/OCCUtils/Construct.py
py4design/py3dmodel/OCCUtils/Image.py
py4design/py3dmodel/OCCUtils/Iteration.py
py4design/py3dmodel/OCCUtils/Topology.py
py4design/py3dmodel/OCCUtils/__init__.py
py4design/py3dmodel/OCCUtils/base.py
py4design/py3dmodel/OCCUtils/edge.py
py4design/py3dmodel/OCCUtils/face.py
py4design/py3dmodel/OCCUtils/shell.py
py4design/py3dmodel/OCCUtils/solid.py
py4design/py3dmodel/OCCUtils/types_lut.py
py4design/py3dmodel/OCCUtils/vertex.py
py4design/py3dmodel/OCCUtils/wire.py
py4design/pycitygml/__init__.py
py4design/pycitygml/write_gml.py
py4design/pyoptimise/__init__.py
py4design/pyoptimise/analyse_xml.py
py4design/pyoptimise/draw_graph.py
py4design/pyoptimise/hv.py
py4design/pyoptimise/nsga2.py
py4design-0.25.dist-info/DESCRIPTION.rst
py4design-0.25.dist-info/METADATA
py4design-0.25.dist-info/RECORD
py4design-0.25.dist-info/WHEEL
py4design-0.25.dist-info/metadata.json
py4design-0.25.dist-info/top_level.txt
